<?xml version="1.0"?>
<externalPubs>
  <externalPubAddress>
    <externalPubIdent>
      <externalPubCode pubCodingScheme="ISBN">1501089390</externalPubCode>
      <externalPubTitle>Managing Your First S1000D Project: A Guide for Technical Publications Project Managers</externalPubTitle>
    </externalPubIdent>
    <externalPubAddressItems>
      <externalPubIssueDate year="2014" month="11"/>
      <responsiblePartnerCompany>
        <enterpriseName>CreateSpace Independant Publishing Platform</enterpriseName>
      </responsiblePartnerCompany>
    </externalPubAddressItems>
  </externalPubAddress>
</externalPubs>
